handwritten/__init__.py
handwritten/utils.py
handwritten-0.0.0.dist-info/LICENSE.txt
handwritten-0.0.0.dist-info/METADATA
handwritten-0.0.0.dist-info/WHEEL
handwritten-0.0.0.dist-info/entry_points.txt
handwritten-0.0.0.dist-info/top_level.txt
handwritten-0.0.0.dist-info/RECORD
