Metadata-Version: 2.1
Name: handwritten
Version: 0.0.0
Summary: Handwritten
Home-page: https://github.com/blester125/handwritten
Author: blester125
Author-email: blester125@gmail.com
License: MIT
Download-URL: https://github.com/blester125/handwritten/archive/0.0.0.tar.gz
Platform: UNKNOWN
Classifier: Natural Language :: English
Classifier: Programming Language :: Python :: 3 :: Only
Classifier: License :: OSI Approved :: MIT License
Classifier: Topic :: Scientific/Engineering
Classifier: Intended Audience :: Developers
Classifier: Development Status :: 3 - Alpha
Classifier: Intended Audience :: Science/Research
Classifier: Environment :: Console
Requires-Python: >=3.6
Requires-Dist: tensorflow (>=2.0.0)
Requires-Dist: numpy
Requires-Dist: matplotlib
Provides-Extra: test
Requires-Dist: pytest ; extra == 'test'
